{
  "id": "傍",
  "kanjialiveData": null,
  "jishoData": {
    "query": "傍",
    "found": true,
    "taughtIn": "junior high",
    "jlptLevel": "N1",
    "newspaperFrequencyRank": "1660",
    "strokeCount": 12,
    "meaning": "bystander, side, besides, while, nearby, third person",
    "kunyomi": [
      "かたわ.ら",
      "わき",
      "おか-",
      "はた",
      "そば"
    ],
    "onyomi": [
      "ボウ"
    ],
    "onyomiExamples": [
      {
        "example": "傍聴",
        "reading": "ボウチョウ",
        "meaning": "listening (to a lecture, hearing, parliament session, etc.), attending (without participating), sitting in (e.g. on a meeting), observing"
      },
      {
        "example": "脇見",
        "reading": "ワキミ",
        "meaning": "looking from the side, looking aside"
      },
      {
        "example": "路傍",
        "reading": "ロボウ",
        "meaning": "roadside"
      },
      {
        "example": "道傍",
        "reading": "ドウボウ",
        "meaning": "side of the road, roadside"
      }
    ],
    "kunyomiExamples": [
      {
        "example": "傍ら",
        "reading": "かたわら",
        "meaning": "side, edge, beside, besides, nearby, while (doing), in addition to, at the same time"
      },
      {
        "example": "傍らに",
        "reading": "かたわらに",
        "meaning": "beside, nearby"
      },
      {
        "example": "脇役",
        "reading": "わきやく",
        "meaning": "supporting role (actor), minor role"
      },
      {
        "example": "脇見",
        "reading": "わきみ",
        "meaning": "looking from the side, looking aside"
      },
      {
        "example": "側",
        "reading": "そば",
        "meaning": "near, close, beside, vicinity, proximity, besides, while, third person"
      },
      {
        "example": "端から",
        "reading": "はたから",
        "meaning": "from outside, from the side"
      },
      {
        "example": "側",
        "reading": "そば",
        "meaning": "near, close, beside, vicinity, proximity, besides, while, third person"
      },
      {
        "example": "側から",
        "reading": "そばから",
        "meaning": "as soon as, right after"
      },
      {
        "example": "お側",
        "reading": "おそば",
        "meaning": "near, close, beside, vicinity, proximity, besides, while, attendant, retainer, vassal"
      }
    ],
    "radical": {
      "symbol": "人",
      "forms": [
        "亻"
      ],
      "meaning": "man, human"
    },
    "parts": [
      "亠",
      "冖",
      "化",
      "并",
      "方",
      "立"
    ],
    "strokeOrderDiagramUri": "http://classic.jisho.org/static/images/stroke_diagrams/20621_frames.png",
    "strokeOrderSvgUri": "https://d1w6u4xc3l95km.cloudfront.net/kanji-2015-03/0508d.svg",
    "strokeOrderGifUri": "https://raw.githubusercontent.com/mistval/kanji_images/master/gifs/508d.gif",
    "uri": "https://jisho.org/search/%E5%82%8D%23kanji"
  }
}