{
  "id": "冨",
  "kanjialiveData": null,
  "jishoData": {
    "query": "冨",
    "found": true,
    "newspaperFrequencyRank": "1906",
    "strokeCount": 11,
    "meaning": "enrich, wealthy, abundant",
    "kunyomi": [
      "と.む",
      "とみ"
    ],
    "onyomi": [
      "フ",
      "フウ"
    ],
    "onyomiExamples": [
      {
        "example": "富裕",
        "reading": "フユウ",
        "meaning": "wealthy, rich, affluent"
      },
      {
        "example": "富有",
        "reading": "フユウ",
        "meaning": "rich, wealthy"
      }
    ],
    "kunyomiExamples": [],
    "radical": {
      "symbol": "冖",
      "meaning": "cover"
    },
    "parts": [
      "一",
      "冖",
      "口",
      "田"
    ],
    "strokeOrderDiagramUri": "http://classic.jisho.org/static/images/stroke_diagrams/20904_frames.png",
    "strokeOrderSvgUri": "https://d1w6u4xc3l95km.cloudfront.net/kanji-2015-03/051a8.svg",
    "strokeOrderGifUri": "https://raw.githubusercontent.com/mistval/kanji_images/master/gifs/51a8.gif",
    "uri": "https://jisho.org/search/%E5%86%A8%23kanji"
  }
}