{
  "id": "新",
  "kanjialiveData": {
    "_id": "54317ae2791eba5146ee494e",
    "_rev": "10-7d21a46204b6b531d1a5b178261a7218",
    "rad_name_ja": "おのづくり",
    "grade": 2,
    "hint_group": 1,
    "kunyomi": "ara, atara, atarashii, arata, nii",
    "meaning": "new",
    "kstroke": 13,
    "examples": [
      {
        "japanese": "新聞（しんぶん）",
        "meaning": {
          "english": "newspaper"
        },
        "audio": {
          "opus": "https://media.kanjialive.com/examples_audio/audio-opus/atara(shii)_06_a.opus",
          "aac": "https://media.kanjialive.com/examples_audio/audio-aac/atara(shii)_06_a.aac",
          "ogg": "https://media.kanjialive.com/examples_audio/audio-ogg/atara(shii)_06_a.ogg",
          "mp3": "https://media.kanjialive.com/examples_audio/audio-mp3/atara(shii)_06_a.mp3"
        }
      },
      {
        "japanese": "新年（しんねん）",
        "meaning": {
          "english": "New Year"
        },
        "audio": {
          "opus": "https://media.kanjialive.com/examples_audio/audio-opus/atara(shii)_06_b.opus",
          "aac": "https://media.kanjialive.com/examples_audio/audio-aac/atara(shii)_06_b.aac",
          "ogg": "https://media.kanjialive.com/examples_audio/audio-ogg/atara(shii)_06_b.ogg",
          "mp3": "https://media.kanjialive.com/examples_audio/audio-mp3/atara(shii)_06_b.mp3"
        }
      },
      {
        "japanese": "新製品（しんせいひん）",
        "meaning": {
          "english": "new product"
        },
        "audio": {
          "opus": "https://media.kanjialive.com/examples_audio/audio-opus/atara(shii)_06_c.opus",
          "aac": "https://media.kanjialive.com/examples_audio/audio-aac/atara(shii)_06_c.aac",
          "ogg": "https://media.kanjialive.com/examples_audio/audio-ogg/atara(shii)_06_c.ogg",
          "mp3": "https://media.kanjialive.com/examples_audio/audio-mp3/atara(shii)_06_c.mp3"
        }
      },
      {
        "japanese": "新幹線（しんかんせん）",
        "meaning": {
          "english": "Shinkansen"
        },
        "audio": {
          "opus": "https://media.kanjialive.com/examples_audio/audio-opus/atara(shii)_06_d.opus",
          "aac": "https://media.kanjialive.com/examples_audio/audio-aac/atara(shii)_06_d.aac",
          "ogg": "https://media.kanjialive.com/examples_audio/audio-ogg/atara(shii)_06_d.ogg",
          "mp3": "https://media.kanjialive.com/examples_audio/audio-mp3/atara(shii)_06_d.mp3"
        }
      },
      {
        "japanese": "最新式（さいしんしき）",
        "meaning": {
          "english": "latest style"
        },
        "audio": {
          "opus": "https://media.kanjialive.com/examples_audio/audio-opus/atara(shii)_06_e.opus",
          "aac": "https://media.kanjialive.com/examples_audio/audio-aac/atara(shii)_06_e.aac",
          "ogg": "https://media.kanjialive.com/examples_audio/audio-ogg/atara(shii)_06_e.ogg",
          "mp3": "https://media.kanjialive.com/examples_audio/audio-mp3/atara(shii)_06_e.mp3"
        }
      },
      {
        "japanese": "新鮮な（しんせんな）",
        "meaning": {
          "english": "fresh"
        },
        "audio": {
          "opus": "https://media.kanjialive.com/examples_audio/audio-opus/atara(shii)_06_f.opus",
          "aac": "https://media.kanjialive.com/examples_audio/audio-aac/atara(shii)_06_f.aac",
          "ogg": "https://media.kanjialive.com/examples_audio/audio-ogg/atara(shii)_06_f.ogg",
          "mp3": "https://media.kanjialive.com/examples_audio/audio-mp3/atara(shii)_06_f.mp3"
        }
      },
      {
        "japanese": "革新的な（かくしんてきな）",
        "meaning": {
          "english": "liberal"
        },
        "audio": {
          "opus": "https://media.kanjialive.com/examples_audio/audio-opus/atara(shii)_06_g.opus",
          "aac": "https://media.kanjialive.com/examples_audio/audio-aac/atara(shii)_06_g.aac",
          "ogg": "https://media.kanjialive.com/examples_audio/audio-ogg/atara(shii)_06_g.ogg",
          "mp3": "https://media.kanjialive.com/examples_audio/audio-mp3/atara(shii)_06_g.mp3"
        }
      },
      {
        "japanese": "更新する（こうしんする）",
        "meaning": {
          "english": "update, renew"
        },
        "audio": {
          "opus": "https://media.kanjialive.com/examples_audio/audio-opus/atara(shii)_06_h.opus",
          "aac": "https://media.kanjialive.com/examples_audio/audio-aac/atara(shii)_06_h.aac",
          "ogg": "https://media.kanjialive.com/examples_audio/audio-ogg/atara(shii)_06_h.ogg",
          "mp3": "https://media.kanjialive.com/examples_audio/audio-mp3/atara(shii)_06_h.mp3"
        }
      },
      {
        "japanese": "新しい（あたらしい）",
        "meaning": {
          "english": "new"
        },
        "audio": {
          "opus": "https://media.kanjialive.com/examples_audio/audio-opus/atara(shii)_06_i.opus",
          "aac": "https://media.kanjialive.com/examples_audio/audio-aac/atara(shii)_06_i.aac",
          "ogg": "https://media.kanjialive.com/examples_audio/audio-ogg/atara(shii)_06_i.ogg",
          "mp3": "https://media.kanjialive.com/examples_audio/audio-mp3/atara(shii)_06_i.mp3"
        }
      },
      {
        "japanese": "新たな（あらたな）",
        "meaning": {
          "english": "new"
        },
        "audio": {
          "opus": "https://media.kanjialive.com/examples_audio/audio-opus/atara(shii)_06_j.opus",
          "aac": "https://media.kanjialive.com/examples_audio/audio-aac/atara(shii)_06_j.aac",
          "ogg": "https://media.kanjialive.com/examples_audio/audio-ogg/atara(shii)_06_j.ogg",
          "mp3": "https://media.kanjialive.com/examples_audio/audio-mp3/atara(shii)_06_j.mp3"
        }
      },
      {
        "japanese": "新妻（にいづま）",
        "meaning": {
          "english": "newly-wed wife"
        },
        "audio": {
          "opus": "https://media.kanjialive.com/examples_audio/audio-opus/atara(shii)_06_k.opus",
          "aac": "https://media.kanjialive.com/examples_audio/audio-aac/atara(shii)_06_k.aac",
          "ogg": "https://media.kanjialive.com/examples_audio/audio-ogg/atara(shii)_06_k.ogg",
          "mp3": "https://media.kanjialive.com/examples_audio/audio-mp3/atara(shii)_06_k.mp3"
        }
      }
    ],
    "kunyomi_ja": "あら、あたら、あたらしい、あらた、にい",
    "ka_utf": "新",
    "luminous": "https://www.kenkyusha.co.jp/collab/KanjiAlive/index.php?book=lumi_waei&method=forward&field=新",
    "rad_name_search": [
      "onozukuri"
    ],
    "rad_order": 89,
    "txt_books": [
      {
        "chapter": "17",
        "txt_bk": "lesson"
      },
      {
        "chapter": "8",
        "txt_bk": "txtBasicKanji"
      },
      {
        "chapter": "14",
        "txt_bk": "txtAd2"
      },
      {
        "chapter": "8",
        "txt_bk": "txtGenki"
      },
      {
        "chapter": "6",
        "txt_bk": "txtSFJ1"
      },
      {
        "chapter": "6",
        "txt_bk": "txtSFJ"
      },
      {
        "chapter": "6",
        "txt_bk": "txtHarrison"
      },
      {
        "chapter": "10",
        "txt_bk": "txtAP"
      },
      {
        "chapter": "6",
        "txt_bk": "txtLookLearn"
      },
      {
        "txt_bk": "cijr",
        "chapter": "6"
      }
    ],
    "kname": "atara(shii)",
    "rad_utf": "⽄",
    "stroketimes": [
      0,
      0.674,
      1.345,
      2.349,
      2.953,
      3.891,
      4.963,
      5.901,
      6.503,
      7.106,
      8.045,
      8.916,
      10.121
    ],
    "kunyomi_ka_display": "あたら、あら、にい",
    "dick": "1166",
    "rad_name": "onozukuri",
    "dicn": "2080",
    "mn_hint": "Part of forest 亲 <span class='note'>(standing 立 tree 木)</span> cut down with an ax 斤 to make room for new growth.",
    "rad_stroke": 4,
    "onyomi_ja": "シン",
    "rad_meaning": "axe",
    "onyomi": "shin",
    "ka_id": "ka_166",
    "rad_position": "tsukuri",
    "rad_position_ja": "つくり",
    "rad_position_search": [
      "tsukuri",
      "tsukuri"
    ],
    "onyomi_search": [
      "shin",
      "shin"
    ],
    "kunyomi_search": [
      "ara",
      "atara",
      "atarashii",
      "arata",
      "nii",
      "ara, atara, atarashii, arata, nii"
    ],
    "meaning_search": [
      "new",
      "new"
    ],
    "onyomi_ja_search": [
      "シン",
      "シン"
    ],
    "kunyomi_ja_search": [
      "あら",
      "あたら",
      "あたらしい",
      "あらた",
      "にい",
      "あら、あたら、あたらしい、あらた、にい"
    ],
    "rad_meaning_search": [
      "axe",
      "axe"
    ],
    "rad_position_ja_search": [
      "つくり",
      "つくり"
    ],
    "rad_name_ja_search": [
      "おのづくり"
    ],
    "textbook_search": [
      "cij",
      "cij:17",
      "cij:c17",
      "bk",
      "bk:8",
      "bk:c8",
      "aij3",
      "aij3:14",
      "aij3:c14",
      "aij3:v2",
      "aij3:v2:14",
      "aij3:v2:c14",
      "gen",
      "gen:8",
      "gen:c8",
      "ap",
      "ap:10",
      "ap:c10",
      "kll",
      "kll:6",
      "kll:c6",
      "cijr",
      "cijr:6",
      "cijr:c6"
    ],
    "rad_name_file": "onozukuri",
    "kanji": {
      "character": "新",
      "meaning": {
        "english": "new"
      },
      "strokes": {
        "count": 13,
        "timings": [
          0,
          0.674,
          1.345,
          2.349,
          2.953,
          3.891,
          4.963,
          5.901,
          6.503,
          7.106,
          8.045,
          8.916,
          10.121
        ],
        "images": [
          "https://media.kanjialive.com/kanji_strokes/atara(shii)_1.svg",
          "https://media.kanjialive.com/kanji_strokes/atara(shii)_2.svg",
          "https://media.kanjialive.com/kanji_strokes/atara(shii)_3.svg",
          "https://media.kanjialive.com/kanji_strokes/atara(shii)_4.svg",
          "https://media.kanjialive.com/kanji_strokes/atara(shii)_5.svg",
          "https://media.kanjialive.com/kanji_strokes/atara(shii)_6.svg",
          "https://media.kanjialive.com/kanji_strokes/atara(shii)_7.svg",
          "https://media.kanjialive.com/kanji_strokes/atara(shii)_8.svg",
          "https://media.kanjialive.com/kanji_strokes/atara(shii)_9.svg",
          "https://media.kanjialive.com/kanji_strokes/atara(shii)_10.svg",
          "https://media.kanjialive.com/kanji_strokes/atara(shii)_11.svg",
          "https://media.kanjialive.com/kanji_strokes/atara(shii)_12.svg",
          "https://media.kanjialive.com/kanji_strokes/atara(shii)_13.svg"
        ]
      },
      "onyomi": {
        "romaji": "shin",
        "katakana": "シン"
      },
      "kunyomi": {
        "romaji": "ara, atara, atarashii, arata, nii",
        "hiragana": "あたら、あら、にい"
      },
      "video": {
        "poster": "https://media.kanjialive.com/kanji_strokes/atara(shii)_13.svg",
        "mp4": "https://media.kanjialive.com/kanji_animations/kanji_mp4/atara(shii)_00.mp4",
        "webm": "https://media.kanjialive.com/kanji_animations/kanji_webm/atara(shii)_00.webm"
      }
    },
    "radical": {
      "character": "⽄",
      "strokes": 4,
      "image": "https://media.kanjialive.com/radical_character/onozukuri.svg",
      "position": {
        "hiragana": "つくり",
        "romaji": "tsukuri",
        "icon": "https://media.kanjialive.com/rad_positions/tsukuri.svg"
      },
      "name": {
        "hiragana": "おのづくり",
        "romaji": "onozukuri"
      },
      "meaning": {
        "english": "axe"
      },
      "animation": [
        "https://media.kanjialive.com/rad_frames/onozukuri0.svg",
        "https://media.kanjialive.com/rad_frames/onozukuri1.svg",
        "https://media.kanjialive.com/rad_frames/onozukuri2.svg"
      ]
    },
    "references": {
      "grade": 2,
      "kodansha": "1166",
      "classic_nelson": "2080"
    }
  },
  "jishoData": {
    "query": "新",
    "found": true,
    "taughtIn": "grade 2",
    "jlptLevel": "N4",
    "newspaperFrequencyRank": "51",
    "strokeCount": 13,
    "meaning": "new",
    "kunyomi": [
      "あたら.しい",
      "あら.た",
      "あら-",
      "にい-"
    ],
    "onyomi": [
      "シン"
    ],
    "onyomiExamples": [
      {
        "example": "新",
        "reading": "シン",
        "meaning": "new, neo-, newness, novelty, Gregorian calendar, Xin dynasty (of China; 9-23 CE), Hsin dynasty"
      },
      {
        "example": "新鋭",
        "reading": "シンエイ",
        "meaning": "young and energetic, up-and-coming, new and excellent, newly produced, up-and-comer"
      },
      {
        "example": "維新",
        "reading": "イシン",
        "meaning": "reformation, revolution, renewal, Meiji Restoration, Nippon Ishin no Kai, Japan Innovation Party"
      },
      {
        "example": "改新",
        "reading": "カイシン",
        "meaning": "reformation"
      }
    ],
    "kunyomiExamples": [
      {
        "example": "新しい",
        "reading": "あたらしい",
        "meaning": "new, novel, fresh, recent, latest, up-to-date, modern"
      },
      {
        "example": "新しい女",
        "reading": "あたらしいおんな",
        "meaning": "liberated woman"
      },
      {
        "example": "新た",
        "reading": "あらた",
        "meaning": "new, fresh, novel"
      },
      {
        "example": "新田",
        "reading": "しんでん",
        "meaning": "new rice field, newly developed rice field, wasteland or marshland newly reclaimed as a rice field (Edo period)"
      }
    ],
    "radical": {
      "symbol": "斤",
      "meaning": "axe"
    },
    "parts": [
      "亠",
      "并",
      "斤",
      "木",
      "立",
      "辛"
    ],
    "strokeOrderDiagramUri": "http://classic.jisho.org/static/images/stroke_diagrams/26032_frames.png",
    "strokeOrderSvgUri": "https://d1w6u4xc3l95km.cloudfront.net/kanji-2015-03/065b0.svg",
    "strokeOrderGifUri": "https://raw.githubusercontent.com/mistval/kanji_images/master/gifs/65b0.gif",
    "uri": "https://jisho.org/search/%E6%96%B0%23kanji"
  }
}