{
  "id": "浸",
  "kanjialiveData": null,
  "jishoData": {
    "query": "浸",
    "found": true,
    "taughtIn": "junior high",
    "jlptLevel": "N1",
    "newspaperFrequencyRank": "1447",
    "strokeCount": 10,
    "meaning": "immersed, soak, dip, steep, moisten, wet, dunk",
    "kunyomi": [
      "ひた.す",
      "ひた.る",
      "つ.かる"
    ],
    "onyomi": [
      "シン"
    ],
    "onyomiExamples": [
      {
        "example": "浸透",
        "reading": "シントウ",
        "meaning": "permeation (of thought, ideology, culture, etc.), infiltration (e.g. of ideas), spread, penetration (e.g. into a market), pervasion, permeation (of a liquid, etc.), soaking, percolation, osmosis"
      },
      {
        "example": "浸水",
        "reading": "シンスイ",
        "meaning": "inundation, submersion, flood"
      },
      {
        "example": "防浸",
        "reading": "ボウシン",
        "meaning": "watertight, waterproof"
      },
      {
        "example": "液浸",
        "reading": "エキシン",
        "meaning": "immersion, dipping, in microscopy, immersing both the objective lens and the specimen in a liquid to increase the numerical aperture, in photolithography, filling the air gap between the final lens and the wafer surface with a liquid to increase the resolution"
      }
    ],
    "kunyomiExamples": [
      {
        "example": "浸す",
        "reading": "ひたす",
        "meaning": "to soak, to dip, to steep, to immerse, to moisten, to wet"
      },
      {
        "example": "浸る",
        "reading": "ひたる",
        "meaning": "to be soaked in, to be flooded, to be submerged, to be immersed in (joy, memories, alcohol, etc.), to give oneself over to, to bask in"
      },
      {
        "example": "浸かる",
        "reading": "つかる",
        "meaning": "to be submerged, to be soaked, to be pickled, to be well seasoned, to be totally immersed (in a condition, e.g. laziness)"
      }
    ],
    "radical": {
      "symbol": "水",
      "forms": [
        "氵",
        "氺"
      ],
      "meaning": "water"
    },
    "parts": [
      "ヨ",
      "冖",
      "又",
      "汁"
    ],
    "strokeOrderDiagramUri": "http://classic.jisho.org/static/images/stroke_diagrams/28024_frames.png",
    "strokeOrderSvgUri": "https://d1w6u4xc3l95km.cloudfront.net/kanji-2015-03/06d78.svg",
    "strokeOrderGifUri": "https://raw.githubusercontent.com/mistval/kanji_images/master/gifs/6d78.gif",
    "uri": "https://jisho.org/search/%E6%B5%B8%23kanji"
  }
}