{
  "id": "湾",
  "kanjialiveData": {
    "_id": "54317adf791eba5146ee491a",
    "_rev": "10-a9be215920d0c38eee3e3c89068126ac",
    "rad_name_ja": "さんずい",
    "grade": null,
    "hint_group": 1,
    "kunyomi": "n/a",
    "meaning": "bay",
    "kstroke": 12,
    "examples": [
      {
        "japanese": "湾（わん）",
        "meaning": {
          "english": "bay, gulf, inlet"
        },
        "audio": {
          "opus": "https://media.kanjialive.com/examples_audio/audio-opus/(mekishiko)wan_06_a.opus",
          "aac": "https://media.kanjialive.com/examples_audio/audio-aac/(mekishiko)wan_06_a.aac",
          "ogg": "https://media.kanjialive.com/examples_audio/audio-ogg/(mekishiko)wan_06_a.ogg",
          "mp3": "https://media.kanjialive.com/examples_audio/audio-mp3/(mekishiko)wan_06_a.mp3"
        }
      },
      {
        "japanese": "湾内（わんない）",
        "meaning": {
          "english": "inside the bay"
        },
        "audio": {
          "opus": "https://media.kanjialive.com/examples_audio/audio-opus/(mekishiko)wan_06_b.opus",
          "aac": "https://media.kanjialive.com/examples_audio/audio-aac/(mekishiko)wan_06_b.aac",
          "ogg": "https://media.kanjialive.com/examples_audio/audio-ogg/(mekishiko)wan_06_b.ogg",
          "mp3": "https://media.kanjialive.com/examples_audio/audio-mp3/(mekishiko)wan_06_b.mp3"
        }
      },
      {
        "japanese": "湾口（わんこう）",
        "meaning": {
          "english": "entrance or mouth of a bay"
        },
        "audio": {
          "opus": "https://media.kanjialive.com/examples_audio/audio-opus/(mekishiko)wan_06_c.opus",
          "aac": "https://media.kanjialive.com/examples_audio/audio-aac/(mekishiko)wan_06_c.aac",
          "ogg": "https://media.kanjialive.com/examples_audio/audio-ogg/(mekishiko)wan_06_c.ogg",
          "mp3": "https://media.kanjialive.com/examples_audio/audio-mp3/(mekishiko)wan_06_c.mp3"
        }
      },
      {
        "japanese": "台湾（たいわん）",
        "meaning": {
          "english": "Taiwan"
        },
        "audio": {
          "opus": "https://media.kanjialive.com/examples_audio/audio-opus/(mekishiko)wan_06_d.opus",
          "aac": "https://media.kanjialive.com/examples_audio/audio-aac/(mekishiko)wan_06_d.aac",
          "ogg": "https://media.kanjialive.com/examples_audio/audio-ogg/(mekishiko)wan_06_d.ogg",
          "mp3": "https://media.kanjialive.com/examples_audio/audio-mp3/(mekishiko)wan_06_d.mp3"
        }
      },
      {
        "japanese": "港湾局（こうわんきょく）",
        "meaning": {
          "english": "Port and Harbor Authority"
        },
        "audio": {
          "opus": "https://media.kanjialive.com/examples_audio/audio-opus/(mekishiko)wan_06_e.opus",
          "aac": "https://media.kanjialive.com/examples_audio/audio-aac/(mekishiko)wan_06_e.aac",
          "ogg": "https://media.kanjialive.com/examples_audio/audio-ogg/(mekishiko)wan_06_e.ogg",
          "mp3": "https://media.kanjialive.com/examples_audio/audio-mp3/(mekishiko)wan_06_e.mp3"
        }
      },
      {
        "japanese": "東京湾（とうきょうわん）",
        "meaning": {
          "english": "Tokyo Bay"
        },
        "audio": {
          "opus": "https://media.kanjialive.com/examples_audio/audio-opus/(mekishiko)wan_06_f.opus",
          "aac": "https://media.kanjialive.com/examples_audio/audio-aac/(mekishiko)wan_06_f.aac",
          "ogg": "https://media.kanjialive.com/examples_audio/audio-ogg/(mekishiko)wan_06_f.ogg",
          "mp3": "https://media.kanjialive.com/examples_audio/audio-mp3/(mekishiko)wan_06_f.mp3"
        }
      },
      {
        "japanese": "湾曲する（わんきょくする）",
        "meaning": {
          "english": "curve [v.i.]"
        },
        "audio": {
          "opus": "https://media.kanjialive.com/examples_audio/audio-opus/(mekishiko)wan_06_g.opus",
          "aac": "https://media.kanjialive.com/examples_audio/audio-aac/(mekishiko)wan_06_g.aac",
          "ogg": "https://media.kanjialive.com/examples_audio/audio-ogg/(mekishiko)wan_06_g.ogg",
          "mp3": "https://media.kanjialive.com/examples_audio/audio-mp3/(mekishiko)wan_06_g.mp3"
        }
      }
    ],
    "kunyomi_ja": "",
    "ka_utf": "湾",
    "luminous": "https://www.kenkyusha.co.jp/collab/KanjiAlive/index.php?book=lumi_waei&method=forward&field=湾",
    "rad_name_search": [
      "sanzui"
    ],
    "rad_order": 76,
    "txt_books": [],
    "kname": "(mekishiko)wan",
    "rad_utf": "⺡",
    "stroketimes": [
      0,
      1,
      1.933333,
      3.066667,
      4.666667,
      6.133333,
      7.466667,
      8.466667,
      9.6,
      10.6,
      11.933333,
      14.133333,
      16
    ],
    "kunyomi_ka_display": "n/a",
    "dick": "447",
    "rad_name": "sanzui",
    "dicn": "2627",
    "mn_hint": "A part of the ocean シ enclosed by a curve in the land like 亦 <span class='note'>(orig. \"again\")</span> a bow 弓.",
    "rad_stroke": 3,
    "onyomi_ja": "ワン",
    "rad_meaning": "water",
    "onyomi": "wan",
    "ka_id": "ka_1230",
    "rad_position": "hen",
    "rad_position_ja": "へん",
    "rad_position_search": [
      "hen",
      "hen"
    ],
    "onyomi_search": [
      "wan",
      "wan"
    ],
    "kunyomi_search": [
      "n/a",
      "n/a"
    ],
    "meaning_search": [
      "bay",
      "bay"
    ],
    "onyomi_ja_search": [
      "ワン",
      "ワン"
    ],
    "kunyomi_ja_search": [
      ""
    ],
    "rad_meaning_search": [
      "water",
      "water"
    ],
    "rad_position_ja_search": [
      "へん",
      "へん"
    ],
    "rad_name_ja_search": [
      "さんずい"
    ],
    "textbook_search": [],
    "rad_name_file": "sanzui",
    "kanji": {
      "character": "湾",
      "meaning": {
        "english": "bay"
      },
      "strokes": {
        "count": 12,
        "timings": [
          0,
          1,
          1.933333,
          3.066667,
          4.666667,
          6.133333,
          7.466667,
          8.466667,
          9.6,
          10.6,
          11.933333,
          14.133333,
          16
        ],
        "images": [
          "https://media.kanjialive.com/kanji_strokes/(mekishiko)wan_1.svg",
          "https://media.kanjialive.com/kanji_strokes/(mekishiko)wan_2.svg",
          "https://media.kanjialive.com/kanji_strokes/(mekishiko)wan_3.svg",
          "https://media.kanjialive.com/kanji_strokes/(mekishiko)wan_4.svg",
          "https://media.kanjialive.com/kanji_strokes/(mekishiko)wan_5.svg",
          "https://media.kanjialive.com/kanji_strokes/(mekishiko)wan_6.svg",
          "https://media.kanjialive.com/kanji_strokes/(mekishiko)wan_7.svg",
          "https://media.kanjialive.com/kanji_strokes/(mekishiko)wan_8.svg",
          "https://media.kanjialive.com/kanji_strokes/(mekishiko)wan_9.svg",
          "https://media.kanjialive.com/kanji_strokes/(mekishiko)wan_10.svg",
          "https://media.kanjialive.com/kanji_strokes/(mekishiko)wan_11.svg",
          "https://media.kanjialive.com/kanji_strokes/(mekishiko)wan_12.svg"
        ]
      },
      "onyomi": {
        "romaji": "wan",
        "katakana": "ワン"
      },
      "kunyomi": {
        "romaji": "n/a",
        "hiragana": "n/a"
      },
      "video": {
        "poster": "https://media.kanjialive.com/kanji_strokes/(mekishiko)wan_12.svg",
        "mp4": "https://media.kanjialive.com/kanji_animations/kanji_mp4/(mekishiko)wan_00.mp4",
        "webm": "https://media.kanjialive.com/kanji_animations/kanji_webm/(mekishiko)wan_00.webm"
      }
    },
    "radical": {
      "character": "⺡",
      "strokes": 3,
      "image": "https://media.kanjialive.com/radical_character/sanzui.svg",
      "position": {
        "hiragana": "へん",
        "romaji": "hen",
        "icon": "https://media.kanjialive.com/rad_positions/hen.svg"
      },
      "name": {
        "hiragana": "さんずい",
        "romaji": "sanzui"
      },
      "meaning": {
        "english": "water"
      },
      "animation": [
        "https://media.kanjialive.com/rad_frames/sanzui0.svg",
        "https://media.kanjialive.com/rad_frames/sanzui1.svg",
        "https://media.kanjialive.com/rad_frames/sanzui2.svg"
      ]
    },
    "references": {
      "grade": null,
      "kodansha": "447",
      "classic_nelson": "2627"
    }
  },
  "jishoData": {
    "query": "湾",
    "found": true,
    "taughtIn": "junior high",
    "jlptLevel": "N2",
    "newspaperFrequencyRank": "545",
    "strokeCount": 12,
    "meaning": "gulf, bay, inlet",
    "kunyomi": [
      "いりえ"
    ],
    "onyomi": [
      "ワン"
    ],
    "onyomiExamples": [
      {
        "example": "湾",
        "reading": "ワン",
        "meaning": "bay, gulf, inlet"
      },
      {
        "example": "湾岸",
        "reading": "ワンガン",
        "meaning": "gulf coast, bay coast"
      },
      {
        "example": "メキシコ湾",
        "reading": "メキシコワン",
        "meaning": "Gulf of Mexico"
      },
      {
        "example": "海湾",
        "reading": "カイワン",
        "meaning": "gulf, bay"
      }
    ],
    "kunyomiExamples": [],
    "radical": {
      "symbol": "水",
      "forms": [
        "氵",
        "氺"
      ],
      "meaning": "water"
    },
    "parts": [
      "亠",
      "弓",
      "汁"
    ],
    "strokeOrderDiagramUri": "http://classic.jisho.org/static/images/stroke_diagrams/28286_frames.png",
    "strokeOrderSvgUri": "https://d1w6u4xc3l95km.cloudfront.net/kanji-2015-03/06e7e.svg",
    "strokeOrderGifUri": "https://raw.githubusercontent.com/mistval/kanji_images/master/gifs/6e7e.gif",
    "uri": "https://jisho.org/search/%E6%B9%BE%23kanji"
  }
}