{
  "id": "閨",
  "kanjialiveData": null,
  "jishoData": {
    "query": "閨",
    "found": true,
    "strokeCount": 14,
    "meaning": "bedroom",
    "kunyomi": [
      "ねや"
    ],
    "onyomi": [
      "ケイ",
      "ケ"
    ],
    "onyomiExamples": [
      {
        "example": "閨閤",
        "reading": "ケイコウ",
        "meaning": "sleeping quarters, bedroom, woman's living room, woman"
      },
      {
        "example": "閨秀",
        "reading": "ケイシュウ",
        "meaning": "accomplished lady, talented woman, eminent woman"
      },
      {
        "example": "令閨",
        "reading": "レイケイ",
        "meaning": "your wife, his wife, Mrs."
      },
      {
        "example": "空閨",
        "reading": "クウケイ",
        "meaning": "lonely, spouseless bedroom, bedroom of a neglected spouse"
      },
      {
        "example": "閨閤",
        "reading": "ケイコウ",
        "meaning": "sleeping quarters, bedroom, woman's living room, woman"
      },
      {
        "example": "閨秀",
        "reading": "ケイシュウ",
        "meaning": "accomplished lady, talented woman, eminent woman"
      }
    ],
    "kunyomiExamples": [
      {
        "example": "閨",
        "reading": "ねや",
        "meaning": "bedroom (esp. one used by a married couple), sleeping quarters, inner room, room at the back of the house"
      },
      {
        "example": "閨事",
        "reading": "ねやごと",
        "meaning": "sexual intercourse, lovemaking"
      },
      {
        "example": "班女が閨",
        "reading": "はんじょがねや",
        "meaning": "bedroom of a forsaken woman"
      }
    ],
    "radical": {
      "symbol": "門",
      "meaning": "gate"
    },
    "parts": [
      "土",
      "門"
    ],
    "strokeOrderDiagramUri": "http://classic.jisho.org/static/images/stroke_diagrams/38312_frames.png",
    "strokeOrderSvgUri": "https://d1w6u4xc3l95km.cloudfront.net/kanji-2015-03/095a8.svg",
    "strokeOrderGifUri": "https://raw.githubusercontent.com/mistval/kanji_images/master/gifs/95a8.gif",
    "uri": "https://jisho.org/search/%E9%96%A8%23kanji"
  }
}