{
  "id": "鮨",
  "kanjialiveData": null,
  "jishoData": {
    "query": "鮨",
    "found": true,
    "strokeCount": 17,
    "meaning": "sushi, seasoned rice",
    "kunyomi": [
      "すし"
    ],
    "onyomi": [
      "シ",
      "キ"
    ],
    "onyomiExamples": [
      {
        "example": "にぎり寿司",
        "reading": "ニギリズシ",
        "meaning": "nigirizushi, hand-pressed vinegared rice topped with seafood"
      },
      {
        "example": "回転寿司",
        "reading": "カイテンズシ",
        "meaning": "conveyor belt sushi, sushi-go-round, sushi train, kaiten-zushi"
      }
    ],
    "kunyomiExamples": [
      {
        "example": "寿司",
        "reading": "すし",
        "meaning": "sushi, range of dishes made with vinegared rice combined with fish, vegetables, egg, etc."
      },
      {
        "example": "すし酢",
        "reading": "すしず",
        "meaning": "seasoned vinegar used for preparing sushi rice"
      },
      {
        "example": "回転寿司",
        "reading": "かいてんずし",
        "meaning": "conveyor belt sushi, sushi-go-round, sushi train, kaiten-zushi"
      }
    ],
    "radical": {
      "symbol": "魚",
      "meaning": "fish"
    },
    "parts": [
      "匕",
      "日",
      "杰",
      "田",
      "魚"
    ],
    "strokeOrderDiagramUri": "http://classic.jisho.org/static/images/stroke_diagrams/39848_frames.png",
    "strokeOrderSvgUri": "https://d1w6u4xc3l95km.cloudfront.net/kanji-2015-03/09ba8.svg",
    "strokeOrderGifUri": "https://raw.githubusercontent.com/mistval/kanji_images/master/gifs/9ba8.gif",
    "uri": "https://jisho.org/search/%E9%AE%A8%23kanji"
  }
}